{
	"display": {
		"icon": {
			"id": "brown_concrete"
		},
		"title": {
			"text": "Brown Concrete",
			"color": "#FFFFFF"
		},
		"description": {
			"text": "",
			"color": "#FFFFFF"
		},
		"frame": "task",
		"show_toast": false,
		"announce_to_chat": false,
		"hidden": false
	},
	"criteria": {
		"requirement": {
			"trigger": "minecraft:inventory_changed",
			"conditions": {
				"items": [
					{
						"items": [
							"brown_concrete"
						]
					}
				]
			}
		}
	},
	"parent": "aic:colored_blocks/green_concrete",
	"rewards": {
		"function": "aic:advancements/item/brown_concrete"
	}
}
