{
	"display": {
		"icon": {
			"id": "minecraft:brown_egg"
		},
		"title": {
			"text": "Brown Egg",
			"color": "#FFDF00"
		},
		"description": {
			"text": "Obtenir un(e) Brown Egg",
			"color": "#FFFFFF"
		},
		"frame": "task",
		"show_toast": false,
		"announce_to_chat": false,
		"hidden": false
	},
	"criteria": {
		"requirement": {
			"trigger": "minecraft:inventory_changed",
			"conditions": {
				"items": [
					{
						"items": [
							"minecraft:brown_egg"
						]
					}
				]
			}
		}
	},
	"requirements": [
		[
			"requirement"
		]
	]
}
