{
	"display": {
		"icon": {
			"id": "stripped_cherry_wood"
		},
		"title": {
			"text": "Stripped Cherry Wood",
			"color": "#3FE7FF"
		},
		"description": {
			"text": "",
			"color": "#FFFFFF"
		},
		"frame": "task",
		"show_toast": false,
		"announce_to_chat": false,
		"hidden": false
	},
	"criteria": {
		"requirement": {
			"trigger": "minecraft:inventory_changed",
			"conditions": {
				"items": [
					{
						"items": [
							"stripped_cherry_wood"
						]
					}
				]
			}
		}
	},
	"parent": "aic:woods/cherry_wood",
	"rewards": {
		"function": "aic:advancements/item/stripped_cherry_wood"
	}
}
