{
	"display": {
	  "icon": {
		"id": "minecraft:written_book"
	  },
	  "title": {
		"text": "Density IV",
		"color": "#FFFFFF"
	  },
	  "description": {
		"text": "",
		"color": "#FFFFFF"
	  },
	  "frame": "task",
	  "show_toast": false,
	  "announce_to_chat": false,
	  "hidden": false
	},
	"criteria": {
	  "requirement": {
		"trigger": "minecraft:inventory_changed",
      "conditions": {
        "items": [
          {
            "predicates": {
              "minecraft:enchantments": [
                {
                  "enchantments": "density",
                  "levels": 4
                }
              ]
			  }
			}
		  ]
		}
	  }
	},
	"parent": "aic:enchantments/density_3",
	"requirements": [
	  [
		"requirement"
	  ]
	],
	"rewards": {
	  "function": "aic:advancements/item/density_4"
	}
  }